fsubot/__init__.py
fsubot/bot.py
fsubot-0.4.1.dist-info/DESCRIPTION.rst
fsubot-0.4.1.dist-info/METADATA
fsubot-0.4.1.dist-info/RECORD
fsubot-0.4.1.dist-info/WHEEL
fsubot-0.4.1.dist-info/metadata.json
fsubot-0.4.1.dist-info/top_level.txt
